{
  "v": "5.10.1",
  "fr": 30,
  "ip": 0,
  "op": 90,
  "w": 400,
  "h": 200,
  "nm": "Hello Slang Counter",
  "ddd": 0,
  "assets": [],
  "layers": [
    {
      "ddd": 0,
      "ind": 1,
      "ty": 5,
      "nm": "Hello Text",
      "sr": 1,
      "ks": {
        "o": { "a": 0, "k": 0 },
        "r": { "a": 0, "k": 0 },
        "p": { "a": 0, "k": [200, 120, 0] },
        "a": { "a": 0, "k": [0, 0, 0] },
        "s": {
          "a": 1,
          "k": [
            {
              "i": { "x": [0.667], "y": [1] },
              "o": { "x": [0.333], "y": [0] },
              "t": 0,
              "s": [0, 0, 100]
            },
            { "t": 15, "s": [100, 100, 100] }
          ]
        }
      },
      "t": {
        "d": {
          "k": [
            {
              "s": {
                "sz": [400, 80],
                "ps": [-200, -40],
                "s": 60,
                "f": "HelveticaNeue-Bold",
                "t": "hello",
                "j": 2,
                "tr": 0
              },
              "t": 0
            }
          ]
        },
        "p": {},
        "m": { "g": 1, "a": 0 }
      },
      "ao": 0,
      "ip": 0,
      "op": 90,
      "st": 0,
      "bm": 0
    },
    {
      "ddd": 0,
      "ind": 2,
      "ty": 5,
      "nm": "Count Text",
      "sr": 1,
      "ks": {
        "o": { "a": 0, "k": 100 },
        "r": { "a": 0, "k": 0 },
        "p": { "a": 0, "k": [350, 40, 0] },
        "a": { "a": 0, "k": [0, 0, 0] },
        "s": { "a": 0, "k": [100, 100, 100] }
      },
      "t": {
        "d": {
          "k": [
            {
              "s": {
                "sz": [200, 80],
                "ps": [-100, -40],
                "s": 40,
                "f": "HelveticaNeue",
                "t": "0",
                "j": 2,
                "tr": 0
              },
              "t": 0
            },
            {
              "s": {
                "sz": [200, 80],
                "ps": [-100, -40],
                "s": 40,
                "f": "HelveticaNeue",
                "t": "25",
                "j": 2,
                "tr": 0
              },
              "t": 90
            }
          ]
        },
        "p": {},
        "m": { "g": 1, "a": 0 }
      },
      "ao": 0,
      "ip": 0,
      "op": 90,
      "st": 0,
      "bm": 0
    }
  ]
}
